[
  {
    "name": "administrators",
    "path": "/administrators",
    "component": "D:\\\\Escola\\\\Engenharia_Informatica\\\\3ano_1semestre\\\\DAE\\\\ProjDAE\\\\PRC-Client\\\\pages\\\\administrators\\\\index.vue",
    "chunkName": "pages/administrators/index"
  },
  {
    "name": "diseases",
    "path": "/diseases",
    "component": "D:\\\\Escola\\\\Engenharia_Informatica\\\\3ano_1semestre\\\\DAE\\\\ProjDAE\\\\PRC-Client\\\\pages\\\\diseases\\\\index.vue",
    "chunkName": "pages/diseases/index"
  },
  {
    "name": "patients",
    "path": "/patients",
    "component": "D:\\\\Escola\\\\Engenharia_Informatica\\\\3ano_1semestre\\\\DAE\\\\ProjDAE\\\\PRC-Client\\\\pages\\\\patients\\\\index.vue",
    "chunkName": "pages/patients/index"
  },
  {
    "name": "administrators-username",
    "path": "/administrators/:username",
    "component": "D:\\\\Escola\\\\Engenharia_Informatica\\\\3ano_1semestre\\\\DAE\\\\ProjDAE\\\\PRC-Client\\\\pages\\\\administrators\\\\_username.vue",
    "chunkName": "pages/administrators/_username"
  },
  {
    "name": "diseases-code",
    "path": "/diseases/:code",
    "component": "D:\\\\Escola\\\\Engenharia_Informatica\\\\3ano_1semestre\\\\DAE\\\\ProjDAE\\\\PRC-Client\\\\pages\\\\diseases\\\\_code.vue",
    "chunkName": "pages/diseases/_code"
  },
  {
    "name": "patients-username",
    "path": "/patients/:username",
    "component": "D:\\\\Escola\\\\Engenharia_Informatica\\\\3ano_1semestre\\\\DAE\\\\ProjDAE\\\\PRC-Client\\\\pages\\\\patients\\\\_username.vue",
    "chunkName": "pages/patients/_username"
  },
  {
    "name": "index",
    "path": "/",
    "component": "D:\\\\Escola\\\\Engenharia_Informatica\\\\3ano_1semestre\\\\DAE\\\\ProjDAE\\\\PRC-Client\\\\pages\\\\index.vue",
    "chunkName": "pages/index"
  }
]
